odoo/addons/shopinvader_search_engine_update_product_brand_tag/README.rst
odoo/addons/shopinvader_search_engine_update_product_brand_tag/__init__.py
odoo/addons/shopinvader_search_engine_update_product_brand_tag/__manifest__.py
odoo/addons/shopinvader_search_engine_update_product_brand_tag/i18n/shopinvader_search_engine_update_product_brand_tag.pot
odoo/addons/shopinvader_search_engine_update_product_brand_tag/models/__init__.py
odoo/addons/shopinvader_search_engine_update_product_brand_tag/models/product_brand_tag.py
odoo/addons/shopinvader_search_engine_update_product_brand_tag/readme/CONTEXT.md
odoo/addons/shopinvader_search_engine_update_product_brand_tag/readme/CONTRIBUTORS.md
odoo/addons/shopinvader_search_engine_update_product_brand_tag/readme/DESCRIPTION.md
odoo/addons/shopinvader_search_engine_update_product_brand_tag/static/description/icon.png
odoo/addons/shopinvader_search_engine_update_product_brand_tag/static/description/index.html
odoo/addons/shopinvader_search_engine_update_product_brand_tag/tests/__init__.py
odoo/addons/shopinvader_search_engine_update_product_brand_tag/tests/test_update.py
odoo_addon_shopinvader_search_engine_update_product_brand_tag-16.0.1.0.0.2.dist-info/METADATA
odoo_addon_shopinvader_search_engine_update_product_brand_tag-16.0.1.0.0.2.dist-info/WHEEL
odoo_addon_shopinvader_search_engine_update_product_brand_tag-16.0.1.0.0.2.dist-info/top_level.txt
odoo_addon_shopinvader_search_engine_update_product_brand_tag-16.0.1.0.0.2.dist-info/RECORD
